enum_extensions/__init__.py
enum_extensions/auto.py
enum_extensions/bits.py
enum_extensions/constants.py
enum_extensions/enums.py
enum_extensions/flags.py
enum_extensions/members.py
enum_extensions/py.typed
enum_extensions/standard.py
enum_extensions/string.py
enum_extensions/traits.py
enum_extensions/types.py
enum_extensions/typing.py
enum_extensions/unique.py
enum_extensions/utils.py
enum_extensions-0.4.0.dist-info/LICENSE
enum_extensions-0.4.0.dist-info/WHEEL
enum_extensions-0.4.0.dist-info/METADATA
enum_extensions-0.4.0.dist-info/RECORD
