Metadata-Version: 2.1
Name: enum-extensions
Version: 0.4.0
Summary: Enhanced enumerations for Python.
Home-page: https://github.com/nekitdev/enum-extensions
License: MIT
Keywords: python,enum,extensions
Author: nekitdev
Requires-Python: >=3.7
Classifier: Development Status :: 4 - Beta
Classifier: Intended Audience :: Developers
Classifier: License :: OSI Approved :: MIT License
Classifier: Operating System :: OS Independent
Classifier: Programming Language :: Python :: 3
Classifier: Programming Language :: Python :: 3.7
Classifier: Programming Language :: Python :: 3.8
Classifier: Programming Language :: Python :: 3.9
Classifier: Programming Language :: Python :: 3.10
Classifier: Programming Language :: Python :: 3.11
Classifier: Topic :: Utilities
Classifier: Typing :: Typed
Requires-Dist: named (>=1.1.0)
Requires-Dist: solus (>=1.0.1)
Requires-Dist: typing-extensions (>=4.3.0)
Project-URL: Documentation, https://nekitdev.github.io/enum-extensions
Project-URL: Discord, https://nekit.dev/discord
Project-URL: Funding, https://patreon.com/nekitdev
Project-URL: Issues, https://github.com/nekitdev/enum-extensions/issues
Project-URL: Repository, https://github.com/nekitdev/enum-extensions
